Workbook
Name SamplesMonth1: 'Inputs'!$B$5
Name SamplesMonth2Plus: 'Inputs'!$B$6
Name ConversionRate: 'Inputs'!$B$7
Name FlywheelAffiliates: 'Inputs'!$B$8
Name TimeToFirstSale: 'Inputs'!$B$9
Name AttritionRate: 'Inputs'!$B$10
Name SalesPerAffiliate: 'Inputs'!$B$14
Name GrossAOV: 'Inputs'!$B$15
Name RollingWindow: 'Inputs'!$B$16
Name DiscountRedemptionRate: 'Inputs'!$B$21
Name MissionCompletionRate: 'Inputs'!$B$22
Name CostPerSample: 'Inputs'!$B$27
Name VIPLevels: 'VIP Levels'!$B$5:$D$9
Name WelcomeRewards: 'VIP Levels'!$A$14:$N$18

Sheet Inputs
A1: LOYALTY PROGRAM FINANCIAL MODEL - INPUTS DASHBOARD
A3: ACQUISITION INPUTS
A4: Parameter | B4: Value | C4: Unit | D4: Description
A5: Samples Sent - Month 1 | B5: 150 | C5: samples | D5: Initial month sample distribution
A6: Samples Sent - Month 2+ | B6: 100 | C6: samples | D6: Ongoing monthly sample distribution
A7: Sample-to-Affiliate Conversion Rate | B7: 0.2 | C7: % | D7: Percentage of samples that convert to affiliates
A8: Flywheel Affiliates per Month | B8: 10 | C8: affiliates | D8: Organic inbound affiliates monthly
A9: Time to First Sale | B9: 14 | C9: days | D9: Lag between conversion and first sale
A10: Affiliate Attrition Rate | B10: 0.05 | C10: % | D10: Monthly churn rate of affiliates
A12: PERFORMANCE INPUTS
A13: Parameter | B13: Value | C13: Unit | D13: Description
A14: Average Sales per Affiliate per Month | B14: 5 | C14: sales | D14: Monthly sales velocity per active affiliate
A15: Gross AOV | B15: 100 | C15: $ | D15: Average order value before discounts
A16: Rolling Window Duration | B16: 30 | C16: days | D16: Time period for VIP level qualification
A19: REDEMPTION & BEHAVIOR INPUTS
A20: Parameter | B20: Value | C20: Unit | D20: Description
A21: Discount Redemption Rate | B21: 0.3 | C21: % | D21: Percentage of discount coupons redeemed
A22: Mission Completion Rate (Default) | B22: 0.25 | C22: % | D22: Default completion rate for missions
A25: COST INPUTS
A26: Parameter | B26: Value | C26: Unit | D26: Description
A27: Cost per Sample | B27: 15 | C27: $ | D27: Cost of each sample sent (product + shipping)
A30: LEGEND
A31: Yellow cells | B31: =Editable inputs
A32: Green cells | B32: =Calculated values

Sheet VIP Levels
A1: VIP LEVEL CONFIGURATION
A3: LEVEL THRESHOLDS & COMMISSION
A4: Level | B4: Name | C4: Sales Threshold | D4: Base Commission %
A5: 1 | B5: Bronze | C5: 0 | D5: 0.1
A6: 2 | B6: Silver | C6: 5 | D6: 0.12
A7: 3 | B7: Gold | C7: 20 | D7: 0.18
A8: 4 | B8: Platinum | C8: 50 | D8: 0.22
A9: 5 | B9: Diamond | C9: 100 | D9: 0.25
A12: WELCOME REWARDS (Per Level)
A13: Level | B13: Comm Boost Qty | C13: Comm Boost % | D13: Comm Boost Days | E13: Gift Card Qty | F13: Gift Card $ | G13: Discount Qty | H13: Discount % | I13: Spark Ads Qty | J13: Spark Ads $ | K13: Physical Gift Qty | L13: Physical Gift $ | M13: Experience Qty | N13: Experience $
A14: Bronze | B14: 1 | C14: 0.1 | D14: 30 | E14: 0 | F14: 0 | G14: 2 | H14: 0.15 | I14: 0 | J14: 0 | K14: 0 | L14: 0 | M14: 0 | N14: 0
A15: Silver | B15: 2 | C15: 0.15 | D15: 30 | E15: 1 | F15: 50 | G15: 2 | H15: 0.15 | I15: 1 | J15: 25 | K15: 0 | L15: 0 | M15: 0 | N15: 0
A16: Gold | B16: 1 | C16: 0.2 | D16: 30 | E16: 1 | F16: 100 | G16: 2 | H16: 0.2 | I16: 1 | J16: 50 | K16: 1 | L16: 50 | M16: 0 | N16: 0
A17: Platinum | B17: 2 | C17: 0.25 | D17: 45 | E17: 2 | F17: 150 | G17: 3 | H17: 0.25 | I17: 2 | J17: 75 | K17: 1 | L17: 75 | M17: 1 | N17: 100
A18: Diamond | B18: 3 | C18: 0.3 | D18: 60 | E18: 2 | F18: 200 | G18: 3 | H18: 0.3 | I18: 2 | J18: 100 | K18: 1 | L18: 100 | M18: 1 | N18: 200

Sheet Missions
A1: MISSION CONFIGURATION
A3: MISSIONS BY VIP LEVEL
A4: VIP Level | B4: Mission Type | C4: Target | D4: Repeatability | E4: Completion Rate | F4: Reward Type | G4: Reward Value | H4: Reward Duration (days) | I4: Active?
A5: Bronze | B5: Videos | C5: 5 | D5: Monthly | E5: 0.25 | F5: Gift Card | G5: 50 | H5: 0 | I5: Yes
A6: Bronze | B6: Likes | C6: 100 | D6: Monthly | E6: 0.2 | F6: Gift Card | G6: 50 | H6: 0 | I6: Yes
A7: Silver | B7: Videos | C7: 10 | D7: Monthly | E7: 0.2 | F7: Commission Boost | G7: 0.2 | H7: 30 | I7: Yes
A8: Silver | B8: Likes | C8: 100 | D8: Monthly | E8: 0.15 | F8: Gift Card | G8: 50 | H8: 0 | I8: Yes
A9: Gold | B9: Sales | C9: 100 | D9: One-time | E9: 0.1 | F9: Commission Boost | G9: 0.3 | H9: 45 | I9: Yes
A10: Gold | B10: Views | C10: 1000 | D10: Monthly | E10: 0.15 | F10: Spark Ads | G10: 50 | H10: 0 | I10: Yes
A11: Platinum | B11: Sales | C11: 200 | D11: One-time | E11: 0.08 | F11: Gift Card | G11: 200 | H11: 0 | I11: Yes
A12: Platinum | B12: Videos | C12: 20 | D12: Monthly | E12: 0.12 | F12: Commission Boost | G12: 0.25 | H12: 30 | I12: Yes
A13: Diamond | B13: Sales | C13: 500 | D13: One-time | E13: 0.05 | F13: Experience | G13: 500 | H13: 0 | I13: Yes
A14: Diamond | B14: Views | C14: 5000 | D14: Monthly | E14: 0.1 | F14: Spark Ads | G14: 100 | H14: 0 | I14: Yes
A26: Mission Types: Videos, Likes, Sales, Views
A27: Repeatability Options: One-time, Weekly, Monthly
A28: Reward Types: Gift Card, Commission Boost, Spark Ads, Discount, Experience

Sheet Affiliate Projection
A1: AFFILIATE PROJECTION (12 MONTHS)
A3: Metric | B3: Month 1 | C3: Month 2 | D3: Month 3 | E3: Month 4 | F3: Month 5 | G3: Month 6 | H3: Month 7 | I3: Month 8 | J3: Month 9 | K3: Month 10 | L3: Month 11 | M3: Month 12
A4: Samples Sent | B4: =Inputs!$B$5 | C4: =Inputs!$B$6 | D4: =Inputs!$B$6 | E4: =Inputs!$B$6 | F4: =Inputs!$B$6 | G4: =Inputs!$B$6 | H4: =Inputs!$B$6 | I4: =Inputs!$B$6 | J4: =Inputs!$B$6 | ... M4: =Inputs!$B$6
A5: New Affiliates (from Samples) | B5: =ROUND(B4*Inputs!$B$7,0) | C5: =ROUND(C4*Inputs!$B$7,0) | D5: =ROUND(D4*Inputs!$B$7,0) | E5: =ROUND(E4*Inputs!$B$7,0) | F5: =ROUND(F4*Inputs!$B$7,0) | G5: =ROUND(G4*Inputs!$B$7,0) | H5: =ROUND(H4*Inputs!$B$7,0) | I5: =ROUND(I4*Inputs!$B$7,0) | ... M5: =ROUND(M4*Inputs!$B$7,0)
A6: Flywheel Affiliates | B6: =Inputs!$B$8 | C6: =Inputs!$B$8 | D6: =Inputs!$B$8 | E6: =Inputs!$B$8 | F6: =Inputs!$B$8 | G6: =Inputs!$B$8 | H6: =Inputs!$B$8 | I6: =Inputs!$B$8 | ... M6: =Inputs!$B$8
A7: Total New Affiliates | B7: =B5+B6 | C7: =C5+C6 | D7: =D5+D6 | E7: =E5+E6 | F7: =F5+F6 | G7: =G5+G6 | H7: =H5+H6 | I7: =I5+I6 | ... M7: =M5+M6
A8: Churned Affiliates | B8: 0 | C8: =ROUND(B9*Inputs!$B$10,0) | D8: =ROUND(C9*Inputs!$B$10,0) | E8: =ROUND(D9*Inputs!$B$10,0) | F8: =ROUND(E9*Inputs!$B$10,0) | G8: =ROUND(F9*Inputs!$B$10,0) | H8: =ROUND(G9*Inputs!$B$10,0) | I8: =ROUND(H9*Inputs!$B$10,0) | J8: =ROUND(I9*Inputs!$B$10,0) | ... M8: =ROUND(L9*Inputs!$B$10,0)
A9: Active Affiliates (End of Month) | B9: =B7-B8 | C9: =B9+C7-C8 | D9: =C9+D7-D8 | E9: =D9+E7-E8 | F9: =E9+F7-F8 | G9: =F9+G7-G8 | H9: =G9+H7-H8 | I9: =H9+I7-I8 | J9: =I9+J7-J8 | ... M9: =L9+M7-M8
A10: Total Sales | B10: =ROUND(B9*Inputs!$B$14,0) | C10: =ROUND(C9*Inputs!$B$14,0) | D10: =ROUND(D9*Inputs!$B$14,0) | E10: =ROUND(E9*Inputs!$B$14,0) | F10: =ROUND(F9*Inputs!$B$14,0) | G10: =ROUND(G9*Inputs!$B$14,0) | H10: =ROUND(H9*Inputs!$B$14,0) | I10: =ROUND(I9*Inputs!$B$14,0) | ... M10: =ROUND(M9*Inputs!$B$14,0)
A11: Affiliates at Bronze | B11: =B9 | C11: =ROUND(C9*0.5,0) | D11: =ROUND(D9*0.5,0) | E11: =ROUND(E9*0.5,0) | F11: =ROUND(F9*0.5,0) | G11: =ROUND(G9*0.5,0) | H11: =ROUND(H9*0.5,0) | I11: =ROUND(I9*0.5,0) | J11: =ROUND(J9*0.5,0) | ... M11: =ROUND(M9*0.5,0)
A12: Affiliates at Silver | B12: 0 | C12: =ROUND(C9*0.25,0) | D12: =ROUND(D9*0.25,0) | E12: =ROUND(E9*0.25,0) | F12: =ROUND(F9*0.25,0) | G12: =ROUND(G9*0.25,0) | H12: =ROUND(H9*0.25,0) | I12: =ROUND(I9*0.25,0) | J12: =ROUND(J9*0.25,0) | ... M12: =ROUND(M9*0.25,0)
A13: Affiliates at Gold | B13: 0 | C13: =ROUND(C9*0.15,0) | D13: =ROUND(D9*0.15,0) | E13: =ROUND(E9*0.15,0) | F13: =ROUND(F9*0.15,0) | G13: =ROUND(G9*0.15,0) | H13: =ROUND(H9*0.15,0) | I13: =ROUND(I9*0.15,0) | J13: =ROUND(J9*0.15,0) | ... M13: =ROUND(M9*0.15,0)
A14: Affiliates at Platinum | B14: 0 | C14: =ROUND(C9*0.07,0) | D14: =ROUND(D9*0.07,0) | E14: =ROUND(E9*0.07,0) | F14: =ROUND(F9*0.07,0) | G14: =ROUND(G9*0.07,0) | H14: =ROUND(H9*0.07,0) | I14: =ROUND(I9*0.07,0) | J14: =ROUND(J9*0.07,0) | ... M14: =ROUND(M9*0.07,0)
A15: Affiliates at Diamond | B15: 0 | C15: =ROUND(C9*0.03,0) | D15: =ROUND(D9*0.03,0) | E15: =ROUND(E9*0.03,0) | F15: =ROUND(F9*0.03,0) | G15: =ROUND(G9*0.03,0) | H15: =ROUND(H9*0.03,0) | I15: =ROUND(I9*0.03,0) | J15: =ROUND(J9*0.03,0) | ... M15: =ROUND(M9*0.03,0)
A16: Level-Up Events | B16: =B7 | C16: =C7+ROUND(B9*0.1,0) | D16: =D7+ROUND(C9*0.1,0) | E16: =E7+ROUND(D9*0.1,0) | F16: =F7+ROUND(E9*0.1,0) | G16: =G7+ROUND(F9*0.1,0) | H16: =H7+ROUND(G9*0.1,0) | I16: =I7+ROUND(H9*0.1,0) | J16: =J7+ROUND(I9*0.1,0) | ... M16: =M7+ROUND(L9*0.1,0)
A17: Demotion Events | B17: 0 | C17: =ROUND(B9*0.05,0) | D17: =ROUND(C9*0.05,0) | E17: =ROUND(D9*0.05,0) | F17: =ROUND(E9*0.05,0) | G17: =ROUND(F9*0.05,0) | H17: =ROUND(G9*0.05,0) | I17: =ROUND(H9*0.05,0) | J17: =ROUND(I9*0.05,0) | ... M17: =ROUND(L9*0.05,0)

Sheet Reward Triggers
A1: REWARD TRIGGERS (12 MONTHS)
A3: Metric | B3: Month 1 | C3: Month 2 | D3: Month 3 | E3: Month 4 | F3: Month 5 | G3: Month 6 | H3: Month 7 | I3: Month 8 | J3: Month 9 | K3: Month 10 | L3: Month 11 | M3: Month 12
A4: --- WELCOME REWARDS ---
A5: Commission Boosts Triggered | B5: ='Affiliate Projection'!B16*2 | C5: ='Affiliate Projection'!C16*2 | D5: ='Affiliate Projection'!D16*2 | E5: ='Affiliate Projection'!E16*2 | F5: ='Affiliate Projection'!F16*2 | G5: ='Affiliate Projection'!G16*2 | H5: ='Affiliate Projection'!H16*2 | I5: ='Affiliate Projection'!I16*2 | ... M5: ='Affiliate Projection'!M16*2
A6: Gift Cards Triggered (One-time) | B6: =ROUND('Affiliate Projection'!B7*0.3,0) | C6: =ROUND('Affiliate Projection'!C7*0.3,0) | D6: =ROUND('Affiliate Projection'!D7*0.3,0) | E6: =ROUND('Affiliate Projection'!E7*0.3,0) | F6: =ROUND('Affiliate Projection'!F7*0.3,0) | G6: =ROUND('Affiliate Projection'!G7*0.3,0) | H6: =ROUND('Affiliate Projection'!H7*0.3,0) | I6: =ROUND('Affiliate Projection'!I7*0.3,0) | ... M6: =ROUND('Affiliate Projection'!M7*0.3,0)
A7: Discount Coupons Triggered | B7: ='Affiliate Projection'!B16*2 | C7: ='Affiliate Projection'!C16*2 | D7: ='Affiliate Projection'!D16*2 | E7: ='Affiliate Projection'!E16*2 | F7: ='Affiliate Projection'!F16*2 | G7: ='Affiliate Projection'!G16*2 | H7: ='Affiliate Projection'!H16*2 | I7: ='Affiliate Projection'!I16*2 | ... M7: ='Affiliate Projection'!M16*2
A8: Spark Ads Triggered | B8: =ROUND('Affiliate Projection'!B16*0.5,0) | C8: =ROUND('Affiliate Projection'!C16*0.5,0) | D8: =ROUND('Affiliate Projection'!D16*0.5,0) | E8: =ROUND('Affiliate Projection'!E16*0.5,0) | F8: =ROUND('Affiliate Projection'!F16*0.5,0) | G8: =ROUND('Affiliate Projection'!G16*0.5,0) | H8: =ROUND('Affiliate Projection'!H16*0.5,0) | I8: =ROUND('Affiliate Projection'!I16*0.5,0) | ... M8: =ROUND('Affiliate Projection'!M16*0.5,0)
A9: Physical Gifts Triggered (One-time) | B9: =ROUND('Affiliate Projection'!B7*0.1,0) | C9: =ROUND('Affiliate Projection'!C7*0.1,0) | D9: =ROUND('Affiliate Projection'!D7*0.1,0) | E9: =ROUND('Affiliate Projection'!E7*0.1,0) | F9: =ROUND('Affiliate Projection'!F7*0.1,0) | G9: =ROUND('Affiliate Projection'!G7*0.1,0) | H9: =ROUND('Affiliate Projection'!H7*0.1,0) | I9: =ROUND('Affiliate Projection'!I7*0.1,0) | ... M9: =ROUND('Affiliate Projection'!M7*0.1,0)
A10: Experiences Triggered (One-time) | B10: =ROUND('Affiliate Projection'!B7*0.03,0) | C10: =ROUND('Affiliate Projection'!C7*0.03,0) | D10: =ROUND('Affiliate Projection'!D7*0.03,0) | E10: =ROUND('Affiliate Projection'!E7*0.03,0) | F10: =ROUND('Affiliate Projection'!F7*0.03,0) | G10: =ROUND('Affiliate Projection'!G7*0.03,0) | H10: =ROUND('Affiliate Projection'!H7*0.03,0) | I10: =ROUND('Affiliate Projection'!I7*0.03,0) | ... M10: =ROUND('Affiliate Projection'!M7*0.03,0)
A12: --- MISSION REWARDS ---
A13: Mission Completions (Bronze) | B13: =ROUND('Affiliate Projection'!B11*Inputs!$B$22*2,0) | C13: =ROUND('Affiliate Projection'!C11*Inputs!$B$22*2,0) | D13: =ROUND('Affiliate Projection'!D11*Inputs!$B$22*2,0) | E13: =ROUND('Affiliate Projection'!E11*Inputs!$B$22*2,0) | F13: =ROUND('Affiliate Projection'!F11*Inputs!$B$22*2,0) | G13: =ROUND('Affiliate Projection'!G11*Inputs!$B$22*2,0) | H13: =ROUND('Affiliate Projection'!H11*Inputs!$B$22*2,0) | I13: =ROUND('Affiliate Projection'!I11*Inputs!$B$22*2,0) | ... M13: =ROUND('Affiliate Projection'!M11*Inputs!$B$22*2,0)
A14: Mission Completions (Silver) | B14: =ROUND('Affiliate Projection'!B12*Inputs!$B$22*2,0) | C14: =ROUND('Affiliate Projection'!C12*Inputs!$B$22*2,0) | D14: =ROUND('Affiliate Projection'!D12*Inputs!$B$22*2,0) | E14: =ROUND('Affiliate Projection'!E12*Inputs!$B$22*2,0) | F14: =ROUND('Affiliate Projection'!F12*Inputs!$B$22*2,0) | G14: =ROUND('Affiliate Projection'!G12*Inputs!$B$22*2,0) | H14: =ROUND('Affiliate Projection'!H12*Inputs!$B$22*2,0) | I14: =ROUND('Affiliate Projection'!I12*Inputs!$B$22*2,0) | ... M14: =ROUND('Affiliate Projection'!M12*Inputs!$B$22*2,0)
A15: Mission Completions (Gold) | B15: =ROUND('Affiliate Projection'!B13*Inputs!$B$22*2,0) | C15: =ROUND('Affiliate Projection'!C13*Inputs!$B$22*2,0) | D15: =ROUND('Affiliate Projection'!D13*Inputs!$B$22*2,0) | E15: =ROUND('Affiliate Projection'!E13*Inputs!$B$22*2,0) | F15: =ROUND('Affiliate Projection'!F13*Inputs!$B$22*2,0) | G15: =ROUND('Affiliate Projection'!G13*Inputs!$B$22*2,0) | H15: =ROUND('Affiliate Projection'!H13*Inputs!$B$22*2,0) | I15: =ROUND('Affiliate Projection'!I13*Inputs!$B$22*2,0) | ... M15: =ROUND('Affiliate Projection'!M13*Inputs!$B$22*2,0)
A16: Mission Completions (Platinum) | B16: =ROUND('Affiliate Projection'!B14*Inputs!$B$22*2,0) | C16: =ROUND('Affiliate Projection'!C14*Inputs!$B$22*2,0) | D16: =ROUND('Affiliate Projection'!D14*Inputs!$B$22*2,0) | E16: =ROUND('Affiliate Projection'!E14*Inputs!$B$22*2,0) | F16: =ROUND('Affiliate Projection'!F14*Inputs!$B$22*2,0) | G16: =ROUND('Affiliate Projection'!G14*Inputs!$B$22*2,0) | H16: =ROUND('Affiliate Projection'!H14*Inputs!$B$22*2,0) | I16: =ROUND('Affiliate Projection'!I14*Inputs!$B$22*2,0) | ... M16: =ROUND('Affiliate Projection'!M14*Inputs!$B$22*2,0)
A17: Mission Completions (Diamond) | B17: =ROUND('Affiliate Projection'!B15*Inputs!$B$22*2,0) | C17: =ROUND('Affiliate Projection'!C15*Inputs!$B$22*2,0) | D17: =ROUND('Affiliate Projection'!D15*Inputs!$B$22*2,0) | E17: =ROUND('Affiliate Projection'!E15*Inputs!$B$22*2,0) | F17: =ROUND('Affiliate Projection'!F15*Inputs!$B$22*2,0) | G17: =ROUND('Affiliate Projection'!G15*Inputs!$B$22*2,0) | H17: =ROUND('Affiliate Projection'!H15*Inputs!$B$22*2,0) | I17: =ROUND('Affiliate Projection'!I15*Inputs!$B$22*2,0) | ... M17: =ROUND('Affiliate Projection'!M15*Inputs!$B$22*2,0)
A18: Total Mission Completions | B18: =SUM(B13:B17) | C18: =SUM(C13:C17) | D18: =SUM(D13:D17) | E18: =SUM(E13:E17) | F18: =SUM(F13:F17) | G18: =SUM(G13:G17) | H18: =SUM(H13:H17) | I18: =SUM(I13:I17) | ... M18: =SUM(M13:M17)

Sheet Revenue
A1: REVENUE PROJECTION (12 MONTHS)
A3: Metric | B3: Month 1 | C3: Month 2 | D3: Month 3 | E3: Month 4 | F3: Month 5 | G3: Month 6 | H3: Month 7 | I3: Month 8 | J3: Month 9 | K3: Month 10 | L3: Month 11 | M3: Month 12
A4: Total Sales Volume | B4: ='Affiliate Projection'!B10 | C4: ='Affiliate Projection'!C10 | D4: ='Affiliate Projection'!D10 | E4: ='Affiliate Projection'!E10 | F4: ='Affiliate Projection'!F10 | G4: ='Affiliate Projection'!G10 | H4: ='Affiliate Projection'!H10 | I4: ='Affiliate Projection'!I10 | ... M4: ='Affiliate Projection'!M10
A5: Gross AOV | B5: =Inputs!$B$15 | C5: =Inputs!$B$15 | D5: =Inputs!$B$15 | E5: =Inputs!$B$15 | F5: =Inputs!$B$15 | G5: =Inputs!$B$15 | H5: =Inputs!$B$15 | I5: =Inputs!$B$15 | ... M5: =Inputs!$B$15
A6: Gross Revenue | B6: =B4*B5 | C6: =C4*C5 | D6: =D4*D5 | E6: =E4*E5 | F6: =F4*F5 | G6: =G4*G5 | H6: =H4*H5 | I6: =I4*I5 | ... M6: =M4*M5
A7: Discount Rate Applied | B7: 0.15 | C7: 0.15 | D7: 0.15 | E7: 0.15 | F7: 0.15 | G7: 0.15 | H7: 0.15 | I7: 0.15 | J7: 0.15 | K7: 0.15 | L7: 0.15 | M7: 0.15
A8: Discounted Sales | B8: =ROUND(B4*Inputs!$B$21,0) | C8: =ROUND(C4*Inputs!$B$21,0) | D8: =ROUND(D4*Inputs!$B$21,0) | E8: =ROUND(E4*Inputs!$B$21,0) | F8: =ROUND(F4*Inputs!$B$21,0) | G8: =ROUND(G4*Inputs!$B$21,0) | H8: =ROUND(H4*Inputs!$B$21,0) | I8: =ROUND(I4*Inputs!$B$21,0) | ... M8: =ROUND(M4*Inputs!$B$21,0)
A9: Net AOV (avg) | B9: =B5*(1-B7*Inputs!$B$21) | C9: =C5*(1-C7*Inputs!$B$21) | D9: =D5*(1-D7*Inputs!$B$21) | E9: =E5*(1-E7*Inputs!$B$21) | F9: =F5*(1-F7*Inputs!$B$21) | G9: =G5*(1-G7*Inputs!$B$21) | H9: =H5*(1-H7*Inputs!$B$21) | I9: =I5*(1-I7*Inputs!$B$21) | ... M9: =M5*(1-M7*Inputs!$B$21)
A10: Net Revenue | B10: =B4*B9 | C10: =C4*C9 | D10: =D4*D9 | E10: =E4*E9 | F10: =F4*F9 | G10: =G4*G9 | H10: =H4*H9 | I10: =I4*I9 | ... M10: =M4*M9
A11: Gross Margin Erosion from Discounts | B11: =B6-B10 | C11: =C6-C10 | D11: =D6-D10 | E11: =E6-E10 | F11: =F6-F10 | G11: =G6-G10 | H11: =H6-H10 | I11: =I6-I10 | ... M11: =M6-M10

Sheet Costs
A1: COST PROJECTION (12 MONTHS)
A3: Metric | B3: Month 1 | C3: Month 2 | D3: Month 3 | E3: Month 4 | F3: Month 5 | G3: Month 6 | H3: Month 7 | I3: Month 8 | J3: Month 9 | K3: Month 10 | L3: Month 11 | M3: Month 12
A4: --- CM1 COSTS (Per Sale) ---
A5: Base Commission Cost | B5: ='Affiliate Projection'!B10*0.12*Revenue!B9 | C5: ='Affiliate Projection'!C10*0.12*Revenue!C9 | D5: ='Affiliate Projection'!D10*0.12*Revenue!D9 | E5: ='Affiliate Projection'!E10*0.12*Revenue!E9 | F5: ='Affiliate Projection'!F10*0.12*Revenue!F9 | G5: ='Affiliate Projection'!G10*0.12*Revenue!G9 | H5: ='Affiliate Projection'!H10*0.12*Revenue!H9 | I5: ='Affiliate Projection'!I10*0.12*Revenue!I9 | ... M5: ='Affiliate Projection'!M10*0.12*Revenue!M9
A6: Commission Boost Cost | B6: ='Reward Triggers'!B5*3*0.15*Revenue!B9 | C6: ='Reward Triggers'!C5*3*0.15*Revenue!C9 | D6: ='Reward Triggers'!D5*3*0.15*Revenue!D9 | E6: ='Reward Triggers'!E5*3*0.15*Revenue!E9 | F6: ='Reward Triggers'!F5*3*0.15*Revenue!F9 | G6: ='Reward Triggers'!G5*3*0.15*Revenue!G9 | H6: ='Reward Triggers'!H5*3*0.15*Revenue!H9 | I6: ='Reward Triggers'!I5*3*0.15*Revenue!I9 | ... M6: ='Reward Triggers'!M5*3*0.15*Revenue!M9
A7: Discount Cost (Margin Erosion) | B7: =Revenue!B11 | C7: =Revenue!C11 | D7: =Revenue!D11 | E7: =Revenue!E11 | F7: =Revenue!F11 | G7: =Revenue!G11 | H7: =Revenue!H11 | I7: =Revenue!I11 | ... M7: =Revenue!M11
A8: Total CM1 Costs | B8: =SUM(B5:B7) | C8: =SUM(C5:C7) | D8: =SUM(D5:D7) | E8: =SUM(E5:E7) | F8: =SUM(F5:F7) | G8: =SUM(G5:G7) | H8: =SUM(H5:H7) | I8: =SUM(I5:I7) | ... M8: =SUM(M5:M7)
A10: --- LOYALTY PROGRAM COSTS ---
A11: Gift Card Cost | B11: ='Reward Triggers'!B6*75+'Reward Triggers'!B18*50*0.3 | C11: ='Reward Triggers'!C6*75+'Reward Triggers'!C18*50*0.3 | D11: ='Reward Triggers'!D6*75+'Reward Triggers'!D18*50*0.3 | E11: ='Reward Triggers'!E6*75+'Reward Triggers'!E18*50*0.3 | F11: ='Reward Triggers'!F6*75+'Reward Triggers'!F18*50*0.3 | G11: ='Reward Triggers'!G6*75+'Reward Triggers'!G18*50*0.3 | H11: ='Reward Triggers'!H6*75+'Reward Triggers'!H18*50*0.3 | I11: ='Reward Triggers'!I6*75+'Reward Triggers'!I18*50*0.3 | ... M11: ='Reward Triggers'!M6*75+'Reward Triggers'!M18*50*0.3
A12: Total Loyalty Program Costs | B12: =B11 | C12: =C11 | D12: =D11 | E12: =E11 | F12: =F11 | G12: =G11 | H12: =H11 | I12: =I11 | ... M12: =M11
A14: --- MARKETING OPEX ---
A15: Spark Ads Cost | B15: ='Reward Triggers'!B8*50+'Reward Triggers'!B18*25*0.2 | C15: ='Reward Triggers'!C8*50+'Reward Triggers'!C18*25*0.2 | D15: ='Reward Triggers'!D8*50+'Reward Triggers'!D18*25*0.2 | E15: ='Reward Triggers'!E8*50+'Reward Triggers'!E18*25*0.2 | F15: ='Reward Triggers'!F8*50+'Reward Triggers'!F18*25*0.2 | G15: ='Reward Triggers'!G8*50+'Reward Triggers'!G18*25*0.2 | H15: ='Reward Triggers'!H8*50+'Reward Triggers'!H18*25*0.2 | I15: ='Reward Triggers'!I8*50+'Reward Triggers'!I18*25*0.2 | ... M15: ='Reward Triggers'!M8*50+'Reward Triggers'!M18*25*0.2
A16: Physical Gift Cost | B16: ='Reward Triggers'!B9*60 | C16: ='Reward Triggers'!C9*60 | D16: ='Reward Triggers'!D9*60 | E16: ='Reward Triggers'!E9*60 | F16: ='Reward Triggers'!F9*60 | G16: ='Reward Triggers'!G9*60 | H16: ='Reward Triggers'!H9*60 | I16: ='Reward Triggers'!I9*60 | ... M16: ='Reward Triggers'!M9*60
A17: Experience Cost | B17: ='Reward Triggers'!B10*150 | C17: ='Reward Triggers'!C10*150 | D17: ='Reward Triggers'!D10*150 | E17: ='Reward Triggers'!E10*150 | F17: ='Reward Triggers'!F10*150 | G17: ='Reward Triggers'!G10*150 | H17: ='Reward Triggers'!H10*150 | I17: ='Reward Triggers'!I10*150 | ... M17: ='Reward Triggers'!M10*150
A18: Sample Cost | B18: ='Affiliate Projection'!B4*Inputs!$B$27 | C18: ='Affiliate Projection'!C4*Inputs!$B$27 | D18: ='Affiliate Projection'!D4*Inputs!$B$27 | E18: ='Affiliate Projection'!E4*Inputs!$B$27 | F18: ='Affiliate Projection'!F4*Inputs!$B$27 | G18: ='Affiliate Projection'!G4*Inputs!$B$27 | H18: ='Affiliate Projection'!H4*Inputs!$B$27 | I18: ='Affiliate Projection'!I4*Inputs!$B$27 | ... M18: ='Affiliate Projection'!M4*Inputs!$B$27
A19: Total Marketing OpEx | B19: =SUM(B15:B18) | C19: =SUM(C15:C18) | D19: =SUM(D15:D18) | E19: =SUM(E15:E18) | F19: =SUM(F15:F18) | G19: =SUM(G15:G18) | H19: =SUM(H15:H18) | I19: =SUM(I15:I18) | ... M19: =SUM(M15:M18)
A21: --- TOTALS ---
A22: Total Program Cost | B22: =B8+B12+B19 | C22: =C8+C12+C19 | D22: =D8+D12+D19 | E22: =E8+E12+E19 | F22: =F8+F12+F19 | G22: =G8+G12+G19 | H22: =H8+H12+H19 | I22: =I8+I12+I19 | ... M22: =M8+M12+M19

Sheet Summary
A1: SUMMARY DASHBOARD
A3: 12-MONTH TOTALS
A4: Metric | B4: Value
A5: Total Samples Sent | B5: =SUM('Affiliate Projection'!B4:M4)
A6: Total New Affiliates | B6: =SUM('Affiliate Projection'!B7:M7)
A7: Active Affiliates (Month 12) | B7: ='Affiliate Projection'!M9
A8: Total Sales | B8: =SUM('Affiliate Projection'!B10:M10)
A10: Gross Revenue | B10: =SUM(Revenue!B6:M6)
A11: Net Revenue | B11: =SUM(Revenue!B10:M10)
A13: Total CM1 Costs | B13: =SUM(Costs!B8:M8)
A14: Total Loyalty Program Costs | B14: =SUM(Costs!B12:M12)
A15: Total Marketing OpEx | B15: =SUM(Costs!B19:M19)
A16: Total Program Cost | B16: =SUM(Costs!B22:M22)
A19: KEY RATIOS
A20: Metric | B20: Value
A21: CM1 as % of Net Revenue | B21: =B13/B11
A22: Total Cost as % of Net Revenue | B22: =B16/B11
A23: Cost per Affiliate (12-mo) | B23: =B16/B6
A24: Revenue per Affiliate (12-mo) | B24: =B11/B6
A25: Sample-to-Affiliate Conversion | B25: =B6/B5
A28: MONTHLY TREND
A29: Metric | B29: M1 | C29: M2 | D29: M3 | E29: M4 | F29: M5 | G29: M6 | H29: M7 | I29: M8 | J29: M9 | K29: M10 | L29: M11 | M29: M12 | N29: Total
A30: Active Affiliates | B30: ='Affiliate Projection'!B9 | C30: ='Affiliate Projection'!C9 | D30: ='Affiliate Projection'!D9 | E30: ='Affiliate Projection'!E9 | F30: ='Affiliate Projection'!F9 | G30: ='Affiliate Projection'!G9 | H30: ='Affiliate Projection'!H9 | I30: ='Affiliate Projection'!I9 | ... M30: ='Affiliate Projection'!M9 | N30: =M30
A31: Total Sales | B31: ='Affiliate Projection'!B10 | C31: ='Affiliate Projection'!C10 | D31: ='Affiliate Projection'!D10 | E31: ='Affiliate Projection'!E10 | F31: ='Affiliate Projection'!F10 | G31: ='Affiliate Projection'!G10 | H31: ='Affiliate Projection'!H10 | I31: ='Affiliate Projection'!I10 | ... M31: ='Affiliate Projection'!M10 | N31: =SUM(B31:M31)
A32: Net Revenue | B32: =Revenue!B10 | C32: =Revenue!C10 | D32: =Revenue!D10 | E32: =Revenue!E10 | F32: =Revenue!F10 | G32: =Revenue!G10 | H32: =Revenue!H10 | I32: =Revenue!I10 | ... M32: =Revenue!M10 | N32: =SUM(B32:M32)
A33: Total Program Cost | B33: =Costs!B22 | C33: =Costs!C22 | D33: =Costs!D22 | E33: =Costs!E22 | F33: =Costs!F22 | G33: =Costs!G22 | H33: =Costs!H22 | I33: =Costs!I22 | ... M33: =Costs!M22 | N33: =SUM(B33:M33)
A34: Cost as % of Revenue | B34: =IF(B32>0,B33/B32,0) | C34: =IF(C32>0,C33/C32,0) | D34: =IF(D32>0,D33/D32,0) | E34: =IF(E32>0,E33/E32,0) | F34: =IF(F32>0,F33/F32,0) | G34: =IF(G32>0,G33/G32,0) | H34: =IF(H32>0,H33/H32,0) | I34: =IF(I32>0,I33/I32,0) | ... N34: =IF(N32>0,N33/N32,0)
