Workbook

Sheet Inputs
A1: LOYALTY PROGRAM FINANCIAL MODEL - INPUTS DASHBOARD
A3: ACQUISITION INPUTS
A4: Parameter | B4: Value | C4: Unit | D4: Description
A5: Samples Sent - Month 1 | B5: 150 | C5: samples | D5: Initial month sample distribution
A6: Samples Sent - Month 2+ | B6: 100 | C6: samples | D6: Ongoing monthly sample distribution
A7: Sample-to-Affiliate Conversion Rate | B7: 0.2 | C7: % | D7: Percentage of samples that convert to affiliates
A8: Flywheel Affiliates per Month | B8: 10 | C8: affiliates | D8: Organic inbound affiliates monthly
A9: Time to First Sale | B9: 14 | C9: days | D9: Lag between conversion and first sale
A10: Affiliate Attrition Rate | B10: 0.05 | C10: % | D10: Monthly churn rate of affiliates
A12: PERFORMANCE INPUTS
A13: Parameter | B13: Value | C13: Unit | D13: Description
A14: Average Sales per Affiliate per Month | B14: 5 | C14: sales | D14: Monthly sales velocity per active affiliate
A15: Gross AOV | B15: 100 | C15: $ | D15: Average order value before discounts
A16: Rolling Window Duration | B16: 30 | C16: days | D16: Time period for VIP level qualification
A19: REDEMPTION & BEHAVIOR INPUTS
A20: Parameter | B20: Value | C20: Unit | D20: Description
A21: Discount Redemption Rate | B21: 0.3 | C21: % | D21: Percentage of discount coupons redeemed
A22: Default Mission Completion Rate | B22: 0.25 | C22: % | D22: Default completion rate for missions
A23: Avg Sales During Commission Boost | B23: 3 | C23: sales | D23: Expected sales an affiliate makes during boost period
A26: COST INPUTS
A27: Parameter | B27: Value | C27: Unit | D27: Description
A28: Cost per Sample | B28: 15 | C28: $ | D28: Cost of each sample sent (product + shipping)
A31: LEVEL DISTRIBUTION ASSUMPTIONS
A32: (Estimated % of affiliates at each level based on sales velocity vs thresholds)
A33: Level | B33: % of Affiliates | C33: Description
A34: Bronze | B34: 0.4 | C34: Affiliates below Silver threshold
A35: Silver | B35: 0.3 | C35: Affiliates at Silver, below Gold
A36: Gold | B36: 0.18 | C36: Affiliates at Gold, below Platinum
A37: Platinum | B37: 0.09 | C37: Affiliates at Platinum, below Diamond
A38: Diamond | B38: 0.03 | C38: Top performers at Diamond
A39: Total (must = 100%) | B39: =SUM(B34:B38)
A42: LEGEND
A43: Yellow cells | B43: =Editable inputs
A44: Green cells | B44: =Calculated values

Sheet VIP Levels
A1: VIP LEVEL CONFIGURATION
A3: LEVEL THRESHOLDS & COMMISSION
A4: Level # | B4: Name | C4: Sales Threshold | D4: Base Commission %
A5: 1 | B5: Bronze | C5: 0 | D5: 0.1
A6: 2 | B6: Silver | C6: 5 | D6: 0.12
A7: 3 | B7: Gold | C7: 20 | D7: 0.18
A8: 4 | B8: Platinum | C8: 50 | D8: 0.22
A9: 5 | B9: Diamond | C9: 100 | D9: 0.25
A12: WELCOME REWARDS (Per Level)
A13: Level | B13: Comm Boost Qty | C13: Comm Boost % | D13: Comm Boost Days | E13: Gift Card Qty | F13: Gift Card $ | G13: Discount Qty | H13: Discount % | I13: Spark Ads Qty | J13: Spark Ads $ | K13: Phys Gift Qty | L13: Phys Gift $ | M13: Experience Qty | N13: Experience $
A14: Bronze | B14: 1 | C14: 0.1 | D14: 30 | E14: 0 | F14: 0 | G14: 2 | H14: 0.15 | I14: 0 | J14: 0 | K14: 0 | L14: 0 | M14: 0 | N14: 0
A15: Silver | B15: 2 | C15: 0.15 | D15: 30 | E15: 1 | F15: 50 | G15: 2 | H15: 0.15 | I15: 1 | J15: 25 | K15: 0 | L15: 0 | M15: 0 | N15: 0
A16: Gold | B16: 1 | C16: 0.2 | D16: 30 | E16: 1 | F16: 100 | G16: 2 | H16: 0.2 | I16: 1 | J16: 50 | K16: 1 | L16: 50 | M16: 0 | N16: 0
A17: Platinum | B17: 2 | C17: 0.25 | D17: 45 | E17: 2 | F17: 150 | G17: 3 | H17: 0.25 | I17: 2 | J17: 75 | K17: 1 | L17: 75 | M17: 1 | N17: 100
A18: Diamond | B18: 3 | C18: 0.3 | D18: 60 | E18: 2 | F18: 200 | G18: 3 | H18: 0.3 | I18: 2 | J18: 100 | K18: 1 | L18: 100 | M18: 1 | N18: 200
A21: WELCOME REWARD SUMMARY (Weighted by Level Distribution)
A22: Weighted Avg Commission Boost % | B22: =SUMPRODUCT(C14:C18,Inputs!$B$34:$B$38)
A23: Weighted Avg Gift Card Value | B23: =SUMPRODUCT(E14:E18*F14:F18,Inputs!$B$34:$B$38)
A24: Weighted Avg Spark Ads Value | B24: =SUMPRODUCT(I14:I18*J14:J18,Inputs!$B$34:$B$38)
A25: Weighted Avg Physical Gift Value | B25: =SUMPRODUCT(K14:K18*L14:L18,Inputs!$B$34:$B$38)
A26: Weighted Avg Experience Value | B26: =SUMPRODUCT(M14:M18*N14:N18,Inputs!$B$34:$B$38)

Sheet Missions
A1: MISSION CONFIGURATION
A3: MISSIONS BY VIP LEVEL
A4: VIP Level | B4: Mission Type | C4: Target | D4: Repeatability | E4: Completion Rate | F4: Reward Type | G4: Reward Value | H4: Reward Duration | I4: Active? | J4: Cost per Completion
A5: Bronze | B5: Videos | C5: 5 | D5: Monthly | E5: 0.25 | F5: Gift Card | G5: 50 | H5: 0 | I5: Yes | J5: =IF(F5="Gift Card",G5,IF(F5="Spark Ads",G5,IF(F5="Commission Boost",G5*Inputs!$B$23*Inputs!$B$15*0.955,0)))
A6: Bronze | B6: Likes | C6: 100 | D6: Monthly | E6: 0.2 | F6: Gift Card | G6: 50 | H6: 0 | I6: Yes | J6: =IF(F6="Gift Card",G6,IF(F6="Spark Ads",G6,IF(F6="Commission Boost",G6*Inputs!$B$23*Inputs!$B$15*0.955,0)))
A7: Silver | B7: Videos | C7: 10 | D7: Monthly | E7: 0.2 | F7: Commission Boost | G7: 0.2 | H7: 30 | I7: Yes | J7: =IF(F7="Gift Card",G7,IF(F7="Spark Ads",G7,IF(F7="Commission Boost",G7*Inputs!$B$23*Inputs!$B$15*0.955,0)))
A8: Silver | B8: Likes | C8: 100 | D8: Monthly | E8: 0.15 | F8: Gift Card | G8: 50 | H8: 0 | I8: Yes | J8: =IF(F8="Gift Card",G8,IF(F8="Spark Ads",G8,IF(F8="Commission Boost",G8*Inputs!$B$23*Inputs!$B$15*0.955,0)))
A9: Gold | B9: Sales | C9: 100 | D9: One-time | E9: 0.1 | F9: Commission Boost | G9: 0.3 | H9: 45 | I9: Yes | J9: =IF(F9="Gift Card",G9,IF(F9="Spark Ads",G9,IF(F9="Commission Boost",G9*Inputs!$B$23*Inputs!$B$15*0.955,0)))
A10: Gold | B10: Views | C10: 1000 | D10: Monthly | E10: 0.15 | F10: Spark Ads | G10: 50 | H10: 0 | I10: Yes | J10: =IF(F10="Gift Card",G10,IF(F10="Spark Ads",G10,IF(F10="Commission Boost",G10*Inputs!$B$23*Inputs!$B$15*0.955,0)))
A11: Platinum | B11: Sales | C11: 200 | D11: One-time | E11: 0.08 | F11: Gift Card | G11: 200 | H11: 0 | I11: Yes | J11: =IF(F11="Gift Card",G11,IF(F11="Spark Ads",G11,IF(F11="Commission Boost",G11*Inputs!$B$23*Inputs!$B$15*0.955,0)))
A12: Platinum | B12: Videos | C12: 20 | D12: Monthly | E12: 0.12 | F12: Commission Boost | G12: 0.25 | H12: 30 | I12: Yes | J12: =IF(F12="Gift Card",G12,IF(F12="Spark Ads",G12,IF(F12="Commission Boost",G12*Inputs!$B$23*Inputs!$B$15*0.955,0)))
A13: Diamond | B13: Sales | C13: 500 | D13: One-time | E13: 0.05 | F13: Gift Card | G13: 300 | H13: 0 | I13: Yes | J13: =IF(F13="Gift Card",G13,IF(F13="Spark Ads",G13,IF(F13="Commission Boost",G13*Inputs!$B$23*Inputs!$B$15*0.955,0)))
A14: Diamond | B14: Views | C14: 5000 | D14: Monthly | E14: 0.1 | F14: Spark Ads | G14: 100 | H14: 0 | I14: Yes | J14: =IF(F14="Gift Card",G14,IF(F14="Spark Ads",G14,IF(F14="Commission Boost",G14*Inputs!$B$23*Inputs!$B$15*0.955,0)))
J15: =IF(F15="Gift Card",G15,IF(F15="Spark Ads",G15,IF(F15="Commission Boost",G15*Inputs!$B$23*Inputs!$B$15*0.955,0)))
J16: =IF(F16="Gift Card",G16,IF(F16="Spark Ads",G16,IF(F16="Commission Boost",G16*Inputs!$B$23*Inputs!$B$15*0.955,0)))
J17: =IF(F17="Gift Card",G17,IF(F17="Spark Ads",G17,IF(F17="Commission Boost",G17*Inputs!$B$23*Inputs!$B$15*0.955,0)))
J18: =IF(F18="Gift Card",G18,IF(F18="Spark Ads",G18,IF(F18="Commission Boost",G18*Inputs!$B$23*Inputs!$B$15*0.955,0)))
J19: =IF(F19="Gift Card",G19,IF(F19="Spark Ads",G19,IF(F19="Commission Boost",G19*Inputs!$B$23*Inputs!$B$15*0.955,0)))
J20: =IF(F20="Gift Card",G20,IF(F20="Spark Ads",G20,IF(F20="Commission Boost",G20*Inputs!$B$23*Inputs!$B$15*0.955,0)))
J21: =IF(F21="Gift Card",G21,IF(F21="Spark Ads",G21,IF(F21="Commission Boost",G21*Inputs!$B$23*Inputs!$B$15*0.955,0)))
J22: =IF(F22="Gift Card",G22,IF(F22="Spark Ads",G22,IF(F22="Commission Boost",G22*Inputs!$B$23*Inputs!$B$15*0.955,0)))
J23: =IF(F23="Gift Card",G23,IF(F23="Spark Ads",G23,IF(F23="Commission Boost",G23*Inputs!$B$23*Inputs!$B$15*0.955,0)))
J24: =IF(F24="Gift Card",G24,IF(F24="Spark Ads",G24,IF(F24="Commission Boost",G24*Inputs!$B$23*Inputs!$B$15*0.955,0)))
A27: MISSION SUMMARY BY LEVEL
A28: Level | B28: Active Missions | C28: Avg Completion Rate | D28: Avg Cost per Completion
A29: Bronze | B29: =COUNTIFS(A$5:A$24,A29,I$5:I$24,"Yes") | C29: =IFERROR(AVERAGEIFS(E$5:E$24,A$5:A$24,A29,I$5:I$24,"Yes"),0) | D29: =IFERROR(AVERAGEIFS(J$5:J$24,A$5:A$24,A29,I$5:I$24,"Yes"),0)
A30: Silver | B30: =COUNTIFS(A$5:A$24,A30,I$5:I$24,"Yes") | C30: =IFERROR(AVERAGEIFS(E$5:E$24,A$5:A$24,A30,I$5:I$24,"Yes"),0) | D30: =IFERROR(AVERAGEIFS(J$5:J$24,A$5:A$24,A30,I$5:I$24,"Yes"),0)
A31: Gold | B31: =COUNTIFS(A$5:A$24,A31,I$5:I$24,"Yes") | C31: =IFERROR(AVERAGEIFS(E$5:E$24,A$5:A$24,A31,I$5:I$24,"Yes"),0) | D31: =IFERROR(AVERAGEIFS(J$5:J$24,A$5:A$24,A31,I$5:I$24,"Yes"),0)
A32: Platinum | B32: =COUNTIFS(A$5:A$24,A32,I$5:I$24,"Yes") | C32: =IFERROR(AVERAGEIFS(E$5:E$24,A$5:A$24,A32,I$5:I$24,"Yes"),0) | D32: =IFERROR(AVERAGEIFS(J$5:J$24,A$5:A$24,A32,I$5:I$24,"Yes"),0)
A33: Diamond | B33: =COUNTIFS(A$5:A$24,A33,I$5:I$24,"Yes") | C33: =IFERROR(AVERAGEIFS(E$5:E$24,A$5:A$24,A33,I$5:I$24,"Yes"),0) | D33: =IFERROR(AVERAGEIFS(J$5:J$24,A$5:A$24,A33,I$5:I$24,"Yes"),0)
A36: Mission Types: Videos, Likes, Sales, Views
A37: Repeatability: One-time, Weekly, Monthly
A38: Reward Types: Gift Card, Commission Boost, Spark Ads

Sheet Affiliate Projection
A1: AFFILIATE PROJECTION (12 MONTHS)
A3: Metric | B3: Month 1 | C3: Month 2 | D3: Month 3 | E3: Month 4 | F3: Month 5 | G3: Month 6 | H3: Month 7 | I3: Month 8 | J3: Month 9 | K3: Month 10 | L3: Month 11 | M3: Month 12
A4: Samples Sent | B4: =Inputs!$B$5 | C4: =Inputs!$B$6 | D4: =Inputs!$B$6 | E4: =Inputs!$B$6 | F4: =Inputs!$B$6 | G4: =Inputs!$B$6 | H4: =Inputs!$B$6 | I4: =Inputs!$B$6 | J4: =Inputs!$B$6 | ... M4: =Inputs!$B$6
A5: New Affiliates (from Samples) | B5: =ROUND(B4*Inputs!$B$7,0) | C5: =ROUND(C4*Inputs!$B$7,0) | D5: =ROUND(D4*Inputs!$B$7,0) | E5: =ROUND(E4*Inputs!$B$7,0) | F5: =ROUND(F4*Inputs!$B$7,0) | G5: =ROUND(G4*Inputs!$B$7,0) | H5: =ROUND(H4*Inputs!$B$7,0) | I5: =ROUND(I4*Inputs!$B$7,0) | ... M5: =ROUND(M4*Inputs!$B$7,0)
A6: Flywheel Affiliates | B6: =Inputs!$B$8 | C6: =Inputs!$B$8 | D6: =Inputs!$B$8 | E6: =Inputs!$B$8 | F6: =Inputs!$B$8 | G6: =Inputs!$B$8 | H6: =Inputs!$B$8 | I6: =Inputs!$B$8 | ... M6: =Inputs!$B$8
A7: Total New Affiliates | B7: =B5+B6 | C7: =C5+C6 | D7: =D5+D6 | E7: =E5+E6 | F7: =F5+F6 | G7: =G5+G6 | H7: =H5+H6 | I7: =I5+I6 | ... M7: =M5+M6
A8: Churned Affiliates | B8: 0 | C8: =ROUND(B9*Inputs!$B$10,0) | D8: =ROUND(C9*Inputs!$B$10,0) | E8: =ROUND(D9*Inputs!$B$10,0) | F8: =ROUND(E9*Inputs!$B$10,0) | G8: =ROUND(F9*Inputs!$B$10,0) | H8: =ROUND(G9*Inputs!$B$10,0) | I8: =ROUND(H9*Inputs!$B$10,0) | J8: =ROUND(I9*Inputs!$B$10,0) | ... M8: =ROUND(L9*Inputs!$B$10,0)
A9: Active Affiliates (End of Month) | B9: =B7-B8 | C9: =B9+C7-C8 | D9: =C9+D7-D8 | E9: =D9+E7-E8 | F9: =E9+F7-F8 | G9: =F9+G7-G8 | H9: =G9+H7-H8 | I9: =H9+I7-I8 | J9: =I9+J7-J8 | ... M9: =L9+M7-M8
A10: Total Sales | B10: =ROUND(B9*Inputs!$B$14,0) | C10: =ROUND(C9*Inputs!$B$14,0) | D10: =ROUND(D9*Inputs!$B$14,0) | E10: =ROUND(E9*Inputs!$B$14,0) | F10: =ROUND(F9*Inputs!$B$14,0) | G10: =ROUND(G9*Inputs!$B$14,0) | H10: =ROUND(H9*Inputs!$B$14,0) | I10: =ROUND(I9*Inputs!$B$14,0) | ... M10: =ROUND(M9*Inputs!$B$14,0)
A11: --- Level Distribution ---
A12: Affiliates at Bronze | B12: =B9 | C12: =ROUND(C9*Inputs!$B$34,0) | D12: =ROUND(D9*Inputs!$B$34,0) | E12: =ROUND(E9*Inputs!$B$34,0) | F12: =ROUND(F9*Inputs!$B$34,0) | G12: =ROUND(G9*Inputs!$B$34,0) | H12: =ROUND(H9*Inputs!$B$34,0) | I12: =ROUND(I9*Inputs!$B$34,0) | J12: =ROUND(J9*Inputs!$B$34,0) | ... M12: =ROUND(M9*Inputs!$B$34,0)
A13: Affiliates at Silver | B13: 0 | C13: =ROUND(C9*Inputs!$B$35,0) | D13: =ROUND(D9*Inputs!$B$35,0) | E13: =ROUND(E9*Inputs!$B$35,0) | F13: =ROUND(F9*Inputs!$B$35,0) | G13: =ROUND(G9*Inputs!$B$35,0) | H13: =ROUND(H9*Inputs!$B$35,0) | I13: =ROUND(I9*Inputs!$B$35,0) | J13: =ROUND(J9*Inputs!$B$35,0) | ... M13: =ROUND(M9*Inputs!$B$35,0)
A14: Affiliates at Gold | B14: 0 | C14: =ROUND(C9*Inputs!$B$36,0) | D14: =ROUND(D9*Inputs!$B$36,0) | E14: =ROUND(E9*Inputs!$B$36,0) | F14: =ROUND(F9*Inputs!$B$36,0) | G14: =ROUND(G9*Inputs!$B$36,0) | H14: =ROUND(H9*Inputs!$B$36,0) | I14: =ROUND(I9*Inputs!$B$36,0) | J14: =ROUND(J9*Inputs!$B$36,0) | ... M14: =ROUND(M9*Inputs!$B$36,0)
A15: Affiliates at Platinum | B15: 0 | C15: =ROUND(C9*Inputs!$B$37,0) | D15: =ROUND(D9*Inputs!$B$37,0) | E15: =ROUND(E9*Inputs!$B$37,0) | F15: =ROUND(F9*Inputs!$B$37,0) | G15: =ROUND(G9*Inputs!$B$37,0) | H15: =ROUND(H9*Inputs!$B$37,0) | I15: =ROUND(I9*Inputs!$B$37,0) | J15: =ROUND(J9*Inputs!$B$37,0) | ... M15: =ROUND(M9*Inputs!$B$37,0)
A16: Affiliates at Diamond | B16: 0 | C16: =ROUND(C9*Inputs!$B$38,0) | D16: =ROUND(D9*Inputs!$B$38,0) | E16: =ROUND(E9*Inputs!$B$38,0) | F16: =ROUND(F9*Inputs!$B$38,0) | G16: =ROUND(G9*Inputs!$B$38,0) | H16: =ROUND(H9*Inputs!$B$38,0) | I16: =ROUND(I9*Inputs!$B$38,0) | J16: =ROUND(J9*Inputs!$B$38,0) | ... M16: =ROUND(M9*Inputs!$B$38,0)
A17: --- Level Events ---
A18: New Affiliate Level-Ups (to Bronze) | B18: =B7 | C18: =C7 | D18: =D7 | E18: =E7 | F18: =F7 | G18: =G7 | H18: =H7 | I18: =I7 | ... M18: =M7
A19: Promotion Events (Bronze to higher) | B19: 0 | C19: =MAX(0,(C13+C14+C15+C16)-(B13+B14+B15+B16)) | D19: =MAX(0,(D13+D14+D15+D16)-(C13+C14+C15+C16)) | E19: =MAX(0,(E13+E14+E15+E16)-(D13+D14+D15+D16)) | F19: =MAX(0,(F13+F14+F15+F16)-(E13+E14+E15+E16)) | G19: =MAX(0,(G13+G14+G15+G16)-(F13+F14+F15+F16)) | H19: =MAX(0,(H13+H14+H15+H16)-(G13+G14+G15+G16)) | I19: =MAX(0,(I13+I14+I15+I16)-(H13+H14+H15+H16)) | J19: =MAX(0,(J13+J14+J15+J16)-(I13+I14+I15+I16)) | ... M19: =MAX(0,(M13+M14+M15+M16)-(L13+L14+L15+L16))
A20: Total Level-Up Events | B20: =B18+B19 | C20: =C18+C19 | D20: =D18+D19 | E20: =E18+E19 | F20: =F18+F19 | G20: =G18+G19 | H20: =H18+H19 | I20: =I18+I19 | ... M20: =M18+M19
A21: Demotion Events | B21: 0 | C21: =MAX(0,(B13+B14+B15+B16)-(C13+C14+C15+C16)) | D21: =MAX(0,(C13+C14+C15+C16)-(D13+D14+D15+D16)) | E21: =MAX(0,(D13+D14+D15+D16)-(E13+E14+E15+E16)) | F21: =MAX(0,(E13+E14+E15+E16)-(F13+F14+F15+F16)) | G21: =MAX(0,(F13+F14+F15+F16)-(G13+G14+G15+G16)) | H21: =MAX(0,(G13+G14+G15+G16)-(H13+H14+H15+H16)) | I21: =MAX(0,(H13+H14+H15+H16)-(I13+I14+I15+I16)) | J21: =MAX(0,(I13+I14+I15+I16)-(J13+J14+J15+J16)) | ... M21: =MAX(0,(L13+L14+L15+L16)-(M13+M14+M15+M16))

Sheet Reward Triggers
A1: REWARD TRIGGERS (12 MONTHS)
A3: Metric | B3: Month 1 | C3: Month 2 | D3: Month 3 | E3: Month 4 | F3: Month 5 | G3: Month 6 | H3: Month 7 | I3: Month 8 | J3: Month 9 | K3: Month 10 | L3: Month 11 | M3: Month 12
A4: --- WELCOME REWARDS (per level-up) ---
A5: Commission Boosts Triggered | B5: =ROUND('Affiliate Projection'!B18*'VIP Levels'!$B$14+'Affiliate Projection'!B19*(SUMPRODUCT('VIP Levels'!$B$15:$B$18,Inputs!$B$35:$B$38)/SUM(Inputs!$B$35:$B$38)),0) | C5: =ROUND('Affiliate Projection'!C18*'VIP Levels'!$B$14+'Affiliate Projection'!C19*(SUMPRODUCT('VIP Levels'!$B$15:$B$18,Inputs!$B$35:$B$38)/SUM(Inputs!$B$35:$B$38)),0) | D5: =ROUND('Affiliate Projection'!D18*'VIP Levels'!$B$14+'Affiliate Projection'!D19*(SUMPRODUCT('VIP Levels'!$B$15:$B$18,Inputs!$B$35:$B$38)/SUM(Inputs!$B$35:$B$38)),0) | E5: =ROUND('Affiliate Projection'!E18*'VIP Levels'!$B$14+'Affiliate Projection'!E19*(SUMPRODUCT('VIP Levels'!$B$15:$B$18,Inputs!$B$35:$B$38)/SUM(Inputs!$B$35:$B$38)),0) | F5: =ROUND('Affiliate Projection'!F18*'VIP Levels'!$B$14+'Affiliate Projection'!F19*(SUMPRODUCT('VIP Levels'!$B$15:$B$18,Inputs!$B$35:$B$38)/SUM(Inputs!$B$35:$B$38)),0) | G5: =ROUND('Affiliate Projection'!G18*'VIP Levels'!$B$14+'Affiliate Projection'!G19*(SUMPRODUCT('VIP Levels'!$B$15:$B$18,Inputs!$B$35:$B$38)/SUM(Inputs!$B$35:$B$38)),0) | H5: =ROUND('Affiliate Projection'!H18*'VIP Levels'!$B$14+'Affiliate Projection'!H19*(SUMPRODUCT('VIP Levels'!$B$15:$B$18,Inputs!$B$35:$B$38)/SUM(Inputs!$B$35:$B$38)),0) | I5: =ROUND('Affiliate Projection'!I18*'VIP Levels'!$B$14+'Affiliate Projection'!I19*(SUMPRODUCT('VIP Levels'!$B$15:$B$18,Inputs!$B$35:$B$38)/SUM(Inputs!$B$35:$B$38)),0) | ... M5: =ROUND('Affiliate Projection'!M18*'VIP Levels'!$B$14+'Affiliate Projection'!M19*(SUMPRODUCT('VIP Levels'!$B$15:$B$18,Inputs!$B$35:$B$38)/SUM(Inputs!$B$35:$B$38)),0)
A6: Gift Cards Triggered | B6: =ROUND('Affiliate Projection'!B19*(SUMPRODUCT('VIP Levels'!$E$15:$E$18,Inputs!$B$35:$B$38)/SUM(Inputs!$B$35:$B$38)),0) | C6: =ROUND('Affiliate Projection'!C19*(SUMPRODUCT('VIP Levels'!$E$15:$E$18,Inputs!$B$35:$B$38)/SUM(Inputs!$B$35:$B$38)),0) | D6: =ROUND('Affiliate Projection'!D19*(SUMPRODUCT('VIP Levels'!$E$15:$E$18,Inputs!$B$35:$B$38)/SUM(Inputs!$B$35:$B$38)),0) | E6: =ROUND('Affiliate Projection'!E19*(SUMPRODUCT('VIP Levels'!$E$15:$E$18,Inputs!$B$35:$B$38)/SUM(Inputs!$B$35:$B$38)),0) | F6: =ROUND('Affiliate Projection'!F19*(SUMPRODUCT('VIP Levels'!$E$15:$E$18,Inputs!$B$35:$B$38)/SUM(Inputs!$B$35:$B$38)),0) | G6: =ROUND('Affiliate Projection'!G19*(SUMPRODUCT('VIP Levels'!$E$15:$E$18,Inputs!$B$35:$B$38)/SUM(Inputs!$B$35:$B$38)),0) | H6: =ROUND('Affiliate Projection'!H19*(SUMPRODUCT('VIP Levels'!$E$15:$E$18,Inputs!$B$35:$B$38)/SUM(Inputs!$B$35:$B$38)),0) | I6: =ROUND('Affiliate Projection'!I19*(SUMPRODUCT('VIP Levels'!$E$15:$E$18,Inputs!$B$35:$B$38)/SUM(Inputs!$B$35:$B$38)),0) | ... M6: =ROUND('Affiliate Projection'!M19*(SUMPRODUCT('VIP Levels'!$E$15:$E$18,Inputs!$B$35:$B$38)/SUM(Inputs!$B$35:$B$38)),0)
A7: Discount Coupons Triggered | B7: =ROUND('Affiliate Projection'!B20*SUMPRODUCT('VIP Levels'!$G$14:$G$18,Inputs!$B$34:$B$38),0) | C7: =ROUND('Affiliate Projection'!C20*SUMPRODUCT('VIP Levels'!$G$14:$G$18,Inputs!$B$34:$B$38),0) | D7: =ROUND('Affiliate Projection'!D20*SUMPRODUCT('VIP Levels'!$G$14:$G$18,Inputs!$B$34:$B$38),0) | E7: =ROUND('Affiliate Projection'!E20*SUMPRODUCT('VIP Levels'!$G$14:$G$18,Inputs!$B$34:$B$38),0) | F7: =ROUND('Affiliate Projection'!F20*SUMPRODUCT('VIP Levels'!$G$14:$G$18,Inputs!$B$34:$B$38),0) | G7: =ROUND('Affiliate Projection'!G20*SUMPRODUCT('VIP Levels'!$G$14:$G$18,Inputs!$B$34:$B$38),0) | H7: =ROUND('Affiliate Projection'!H20*SUMPRODUCT('VIP Levels'!$G$14:$G$18,Inputs!$B$34:$B$38),0) | I7: =ROUND('Affiliate Projection'!I20*SUMPRODUCT('VIP Levels'!$G$14:$G$18,Inputs!$B$34:$B$38),0) | ... M7: =ROUND('Affiliate Projection'!M20*SUMPRODUCT('VIP Levels'!$G$14:$G$18,Inputs!$B$34:$B$38),0)
A8: Spark Ads Triggered | B8: =ROUND('Affiliate Projection'!B19*(SUMPRODUCT('VIP Levels'!$I$15:$I$18,Inputs!$B$35:$B$38)/SUM(Inputs!$B$35:$B$38)),0) | C8: =ROUND('Affiliate Projection'!C19*(SUMPRODUCT('VIP Levels'!$I$15:$I$18,Inputs!$B$35:$B$38)/SUM(Inputs!$B$35:$B$38)),0) | D8: =ROUND('Affiliate Projection'!D19*(SUMPRODUCT('VIP Levels'!$I$15:$I$18,Inputs!$B$35:$B$38)/SUM(Inputs!$B$35:$B$38)),0) | E8: =ROUND('Affiliate Projection'!E19*(SUMPRODUCT('VIP Levels'!$I$15:$I$18,Inputs!$B$35:$B$38)/SUM(Inputs!$B$35:$B$38)),0) | F8: =ROUND('Affiliate Projection'!F19*(SUMPRODUCT('VIP Levels'!$I$15:$I$18,Inputs!$B$35:$B$38)/SUM(Inputs!$B$35:$B$38)),0) | G8: =ROUND('Affiliate Projection'!G19*(SUMPRODUCT('VIP Levels'!$I$15:$I$18,Inputs!$B$35:$B$38)/SUM(Inputs!$B$35:$B$38)),0) | H8: =ROUND('Affiliate Projection'!H19*(SUMPRODUCT('VIP Levels'!$I$15:$I$18,Inputs!$B$35:$B$38)/SUM(Inputs!$B$35:$B$38)),0) | I8: =ROUND('Affiliate Projection'!I19*(SUMPRODUCT('VIP Levels'!$I$15:$I$18,Inputs!$B$35:$B$38)/SUM(Inputs!$B$35:$B$38)),0) | ... M8: =ROUND('Affiliate Projection'!M19*(SUMPRODUCT('VIP Levels'!$I$15:$I$18,Inputs!$B$35:$B$38)/SUM(Inputs!$B$35:$B$38)),0)
A9: Physical Gifts Triggered | B9: =ROUND('Affiliate Projection'!B19*(SUMPRODUCT('VIP Levels'!$K$16:$K$18,Inputs!$B$36:$B$38)/SUM(Inputs!$B$36:$B$38)),0) | C9: =ROUND('Affiliate Projection'!C19*(SUMPRODUCT('VIP Levels'!$K$16:$K$18,Inputs!$B$36:$B$38)/SUM(Inputs!$B$36:$B$38)),0) | D9: =ROUND('Affiliate Projection'!D19*(SUMPRODUCT('VIP Levels'!$K$16:$K$18,Inputs!$B$36:$B$38)/SUM(Inputs!$B$36:$B$38)),0) | E9: =ROUND('Affiliate Projection'!E19*(SUMPRODUCT('VIP Levels'!$K$16:$K$18,Inputs!$B$36:$B$38)/SUM(Inputs!$B$36:$B$38)),0) | F9: =ROUND('Affiliate Projection'!F19*(SUMPRODUCT('VIP Levels'!$K$16:$K$18,Inputs!$B$36:$B$38)/SUM(Inputs!$B$36:$B$38)),0) | G9: =ROUND('Affiliate Projection'!G19*(SUMPRODUCT('VIP Levels'!$K$16:$K$18,Inputs!$B$36:$B$38)/SUM(Inputs!$B$36:$B$38)),0) | H9: =ROUND('Affiliate Projection'!H19*(SUMPRODUCT('VIP Levels'!$K$16:$K$18,Inputs!$B$36:$B$38)/SUM(Inputs!$B$36:$B$38)),0) | I9: =ROUND('Affiliate Projection'!I19*(SUMPRODUCT('VIP Levels'!$K$16:$K$18,Inputs!$B$36:$B$38)/SUM(Inputs!$B$36:$B$38)),0) | ... M9: =ROUND('Affiliate Projection'!M19*(SUMPRODUCT('VIP Levels'!$K$16:$K$18,Inputs!$B$36:$B$38)/SUM(Inputs!$B$36:$B$38)),0)
A10: Experiences Triggered | B10: =ROUND('Affiliate Projection'!B19*(SUMPRODUCT('VIP Levels'!$M$17:$M$18,Inputs!$B$37:$B$38)/SUM(Inputs!$B$37:$B$38)),0) | C10: =ROUND('Affiliate Projection'!C19*(SUMPRODUCT('VIP Levels'!$M$17:$M$18,Inputs!$B$37:$B$38)/SUM(Inputs!$B$37:$B$38)),0) | D10: =ROUND('Affiliate Projection'!D19*(SUMPRODUCT('VIP Levels'!$M$17:$M$18,Inputs!$B$37:$B$38)/SUM(Inputs!$B$37:$B$38)),0) | E10: =ROUND('Affiliate Projection'!E19*(SUMPRODUCT('VIP Levels'!$M$17:$M$18,Inputs!$B$37:$B$38)/SUM(Inputs!$B$37:$B$38)),0) | F10: =ROUND('Affiliate Projection'!F19*(SUMPRODUCT('VIP Levels'!$M$17:$M$18,Inputs!$B$37:$B$38)/SUM(Inputs!$B$37:$B$38)),0) | G10: =ROUND('Affiliate Projection'!G19*(SUMPRODUCT('VIP Levels'!$M$17:$M$18,Inputs!$B$37:$B$38)/SUM(Inputs!$B$37:$B$38)),0) | H10: =ROUND('Affiliate Projection'!H19*(SUMPRODUCT('VIP Levels'!$M$17:$M$18,Inputs!$B$37:$B$38)/SUM(Inputs!$B$37:$B$38)),0) | I10: =ROUND('Affiliate Projection'!I19*(SUMPRODUCT('VIP Levels'!$M$17:$M$18,Inputs!$B$37:$B$38)/SUM(Inputs!$B$37:$B$38)),0) | ... M10: =ROUND('Affiliate Projection'!M19*(SUMPRODUCT('VIP Levels'!$M$17:$M$18,Inputs!$B$37:$B$38)/SUM(Inputs!$B$37:$B$38)),0)
A12: --- MISSION COMPLETIONS ---
A13: Mission Completions (Bronze) | B13: =ROUND('Affiliate Projection'!B12*Missions!$B$29*Missions!$C$29,0) | C13: =ROUND('Affiliate Projection'!C12*Missions!$B$29*Missions!$C$29,0) | D13: =ROUND('Affiliate Projection'!D12*Missions!$B$29*Missions!$C$29,0) | E13: =ROUND('Affiliate Projection'!E12*Missions!$B$29*Missions!$C$29,0) | F13: =ROUND('Affiliate Projection'!F12*Missions!$B$29*Missions!$C$29,0) | G13: =ROUND('Affiliate Projection'!G12*Missions!$B$29*Missions!$C$29,0) | H13: =ROUND('Affiliate Projection'!H12*Missions!$B$29*Missions!$C$29,0) | I13: =ROUND('Affiliate Projection'!I12*Missions!$B$29*Missions!$C$29,0) | ... M13: =ROUND('Affiliate Projection'!M12*Missions!$B$29*Missions!$C$29,0)
A14: Mission Completions (Silver) | B14: =ROUND('Affiliate Projection'!B13*Missions!$B$30*Missions!$C$30,0) | C14: =ROUND('Affiliate Projection'!C13*Missions!$B$30*Missions!$C$30,0) | D14: =ROUND('Affiliate Projection'!D13*Missions!$B$30*Missions!$C$30,0) | E14: =ROUND('Affiliate Projection'!E13*Missions!$B$30*Missions!$C$30,0) | F14: =ROUND('Affiliate Projection'!F13*Missions!$B$30*Missions!$C$30,0) | G14: =ROUND('Affiliate Projection'!G13*Missions!$B$30*Missions!$C$30,0) | H14: =ROUND('Affiliate Projection'!H13*Missions!$B$30*Missions!$C$30,0) | I14: =ROUND('Affiliate Projection'!I13*Missions!$B$30*Missions!$C$30,0) | ... M14: =ROUND('Affiliate Projection'!M13*Missions!$B$30*Missions!$C$30,0)
A15: Mission Completions (Gold) | B15: =ROUND('Affiliate Projection'!B14*Missions!$B$31*Missions!$C$31,0) | C15: =ROUND('Affiliate Projection'!C14*Missions!$B$31*Missions!$C$31,0) | D15: =ROUND('Affiliate Projection'!D14*Missions!$B$31*Missions!$C$31,0) | E15: =ROUND('Affiliate Projection'!E14*Missions!$B$31*Missions!$C$31,0) | F15: =ROUND('Affiliate Projection'!F14*Missions!$B$31*Missions!$C$31,0) | G15: =ROUND('Affiliate Projection'!G14*Missions!$B$31*Missions!$C$31,0) | H15: =ROUND('Affiliate Projection'!H14*Missions!$B$31*Missions!$C$31,0) | I15: =ROUND('Affiliate Projection'!I14*Missions!$B$31*Missions!$C$31,0) | ... M15: =ROUND('Affiliate Projection'!M14*Missions!$B$31*Missions!$C$31,0)
A16: Mission Completions (Platinum) | B16: =ROUND('Affiliate Projection'!B15*Missions!$B$32*Missions!$C$32,0) | C16: =ROUND('Affiliate Projection'!C15*Missions!$B$32*Missions!$C$32,0) | D16: =ROUND('Affiliate Projection'!D15*Missions!$B$32*Missions!$C$32,0) | E16: =ROUND('Affiliate Projection'!E15*Missions!$B$32*Missions!$C$32,0) | F16: =ROUND('Affiliate Projection'!F15*Missions!$B$32*Missions!$C$32,0) | G16: =ROUND('Affiliate Projection'!G15*Missions!$B$32*Missions!$C$32,0) | H16: =ROUND('Affiliate Projection'!H15*Missions!$B$32*Missions!$C$32,0) | I16: =ROUND('Affiliate Projection'!I15*Missions!$B$32*Missions!$C$32,0) | ... M16: =ROUND('Affiliate Projection'!M15*Missions!$B$32*Missions!$C$32,0)
A17: Mission Completions (Diamond) | B17: =ROUND('Affiliate Projection'!B16*Missions!$B$33*Missions!$C$33,0) | C17: =ROUND('Affiliate Projection'!C16*Missions!$B$33*Missions!$C$33,0) | D17: =ROUND('Affiliate Projection'!D16*Missions!$B$33*Missions!$C$33,0) | E17: =ROUND('Affiliate Projection'!E16*Missions!$B$33*Missions!$C$33,0) | F17: =ROUND('Affiliate Projection'!F16*Missions!$B$33*Missions!$C$33,0) | G17: =ROUND('Affiliate Projection'!G16*Missions!$B$33*Missions!$C$33,0) | H17: =ROUND('Affiliate Projection'!H16*Missions!$B$33*Missions!$C$33,0) | I17: =ROUND('Affiliate Projection'!I16*Missions!$B$33*Missions!$C$33,0) | ... M17: =ROUND('Affiliate Projection'!M16*Missions!$B$33*Missions!$C$33,0)
A18: Total Mission Completions | B18: =SUM(B13:B17) | C18: =SUM(C13:C17) | D18: =SUM(D13:D17) | E18: =SUM(E13:E17) | F18: =SUM(F13:F17) | G18: =SUM(G13:G17) | H18: =SUM(H13:H17) | I18: =SUM(I13:I17) | ... M18: =SUM(M13:M17)

Sheet Revenue
A1: REVENUE PROJECTION (12 MONTHS)
A3: Metric | B3: Month 1 | C3: Month 2 | D3: Month 3 | E3: Month 4 | F3: Month 5 | G3: Month 6 | H3: Month 7 | I3: Month 8 | J3: Month 9 | K3: Month 10 | L3: Month 11 | M3: Month 12
A4: Total Sales Volume | B4: ='Affiliate Projection'!B10 | C4: ='Affiliate Projection'!C10 | D4: ='Affiliate Projection'!D10 | E4: ='Affiliate Projection'!E10 | F4: ='Affiliate Projection'!F10 | G4: ='Affiliate Projection'!G10 | H4: ='Affiliate Projection'!H10 | I4: ='Affiliate Projection'!I10 | ... M4: ='Affiliate Projection'!M10
A5: Gross AOV | B5: =Inputs!$B$15 | C5: =Inputs!$B$15 | D5: =Inputs!$B$15 | E5: =Inputs!$B$15 | F5: =Inputs!$B$15 | G5: =Inputs!$B$15 | H5: =Inputs!$B$15 | I5: =Inputs!$B$15 | ... M5: =Inputs!$B$15
A6: Gross Revenue | B6: =B4*B5 | C6: =C4*C5 | D6: =D4*D5 | E6: =E4*E5 | F6: =F4*F5 | G6: =G4*G5 | H6: =H4*H5 | I6: =I4*I5 | ... M6: =M4*M5
A7: Avg Discount % (when redeemed) | B7: =SUMPRODUCT('VIP Levels'!$H$14:$H$18,Inputs!$B$34:$B$38) | C7: =SUMPRODUCT('VIP Levels'!$H$14:$H$18,Inputs!$B$34:$B$38) | D7: =SUMPRODUCT('VIP Levels'!$H$14:$H$18,Inputs!$B$34:$B$38) | E7: =SUMPRODUCT('VIP Levels'!$H$14:$H$18,Inputs!$B$34:$B$38) | F7: =SUMPRODUCT('VIP Levels'!$H$14:$H$18,Inputs!$B$34:$B$38) | G7: =SUMPRODUCT('VIP Levels'!$H$14:$H$18,Inputs!$B$34:$B$38) | H7: =SUMPRODUCT('VIP Levels'!$H$14:$H$18,Inputs!$B$34:$B$38) | I7: =SUMPRODUCT('VIP Levels'!$H$14:$H$18,Inputs!$B$34:$B$38) | ... M7: =SUMPRODUCT('VIP Levels'!$H$14:$H$18,Inputs!$B$34:$B$38)
A8: Discount Redemption Rate | B8: =Inputs!$B$21 | C8: =Inputs!$B$21 | D8: =Inputs!$B$21 | E8: =Inputs!$B$21 | F8: =Inputs!$B$21 | G8: =Inputs!$B$21 | H8: =Inputs!$B$21 | I8: =Inputs!$B$21 | ... M8: =Inputs!$B$21
A9: Discounted Sales Count | B9: =ROUND(B4*B8,0) | C9: =ROUND(C4*C8,0) | D9: =ROUND(D4*D8,0) | E9: =ROUND(E4*E8,0) | F9: =ROUND(F4*F8,0) | G9: =ROUND(G4*G8,0) | H9: =ROUND(H4*H8,0) | I9: =ROUND(I4*I8,0) | ... M9: =ROUND(M4*M8,0)
A10: Net AOV (weighted avg) | B10: =B5*(1-B7*B8) | C10: =C5*(1-C7*C8) | D10: =D5*(1-D7*D8) | E10: =E5*(1-E7*E8) | F10: =F5*(1-F7*F8) | G10: =G5*(1-G7*G8) | H10: =H5*(1-H7*H8) | I10: =I5*(1-I7*I8) | ... M10: =M5*(1-M7*M8)
A11: Net Revenue | B11: =B4*B10 | C11: =C4*C10 | D11: =D4*D10 | E11: =E4*E10 | F11: =F4*F10 | G11: =G4*G10 | H11: =H4*H10 | I11: =I4*I10 | ... M11: =M4*M10
A12: Discount Margin Erosion | B12: =B6-B11 | C12: =C6-C11 | D12: =D6-D11 | E12: =E6-E11 | F12: =F6-F11 | G12: =G6-G11 | H12: =H6-H11 | I12: =I6-I11 | ... M12: =M6-M11

Sheet Costs
A1: COST PROJECTION (12 MONTHS)
A3: Metric | B3: Month 1 | C3: Month 2 | D3: Month 3 | E3: Month 4 | F3: Month 5 | G3: Month 6 | H3: Month 7 | I3: Month 8 | J3: Month 9 | K3: Month 10 | L3: Month 11 | M3: Month 12
A4: --- CM1 COSTS (Per Sale) ---
A5: Base Commission Cost | B5: ='Affiliate Projection'!B10*SUMPRODUCT('VIP Levels'!$D$5:$D$9,Inputs!$B$34:$B$38)*Revenue!B10 | C5: ='Affiliate Projection'!C10*SUMPRODUCT('VIP Levels'!$D$5:$D$9,Inputs!$B$34:$B$38)*Revenue!C10 | D5: ='Affiliate Projection'!D10*SUMPRODUCT('VIP Levels'!$D$5:$D$9,Inputs!$B$34:$B$38)*Revenue!D10 | E5: ='Affiliate Projection'!E10*SUMPRODUCT('VIP Levels'!$D$5:$D$9,Inputs!$B$34:$B$38)*Revenue!E10 | F5: ='Affiliate Projection'!F10*SUMPRODUCT('VIP Levels'!$D$5:$D$9,Inputs!$B$34:$B$38)*Revenue!F10 | G5: ='Affiliate Projection'!G10*SUMPRODUCT('VIP Levels'!$D$5:$D$9,Inputs!$B$34:$B$38)*Revenue!G10 | H5: ='Affiliate Projection'!H10*SUMPRODUCT('VIP Levels'!$D$5:$D$9,Inputs!$B$34:$B$38)*Revenue!H10 | I5: ='Affiliate Projection'!I10*SUMPRODUCT('VIP Levels'!$D$5:$D$9,Inputs!$B$34:$B$38)*Revenue!I10 | ... M5: ='Affiliate Projection'!M10*SUMPRODUCT('VIP Levels'!$D$5:$D$9,Inputs!$B$34:$B$38)*Revenue!M10
A6: Commission Boost Cost (Welcome) | B6: ='Reward Triggers'!B5*Inputs!$B$23*'VIP Levels'!$B$22*Revenue!B10 | C6: ='Reward Triggers'!C5*Inputs!$B$23*'VIP Levels'!$B$22*Revenue!C10 | D6: ='Reward Triggers'!D5*Inputs!$B$23*'VIP Levels'!$B$22*Revenue!D10 | E6: ='Reward Triggers'!E5*Inputs!$B$23*'VIP Levels'!$B$22*Revenue!E10 | F6: ='Reward Triggers'!F5*Inputs!$B$23*'VIP Levels'!$B$22*Revenue!F10 | G6: ='Reward Triggers'!G5*Inputs!$B$23*'VIP Levels'!$B$22*Revenue!G10 | H6: ='Reward Triggers'!H5*Inputs!$B$23*'VIP Levels'!$B$22*Revenue!H10 | I6: ='Reward Triggers'!I5*Inputs!$B$23*'VIP Levels'!$B$22*Revenue!I10 | ... M6: ='Reward Triggers'!M5*Inputs!$B$23*'VIP Levels'!$B$22*Revenue!M10
A7: Commission Boost Cost (Missions) | B7: ='Reward Triggers'!B18*0.3*Inputs!$B$23*'VIP Levels'!$B$22*Revenue!B10 | C7: ='Reward Triggers'!C18*0.3*Inputs!$B$23*'VIP Levels'!$B$22*Revenue!C10 | D7: ='Reward Triggers'!D18*0.3*Inputs!$B$23*'VIP Levels'!$B$22*Revenue!D10 | E7: ='Reward Triggers'!E18*0.3*Inputs!$B$23*'VIP Levels'!$B$22*Revenue!E10 | F7: ='Reward Triggers'!F18*0.3*Inputs!$B$23*'VIP Levels'!$B$22*Revenue!F10 | G7: ='Reward Triggers'!G18*0.3*Inputs!$B$23*'VIP Levels'!$B$22*Revenue!G10 | H7: ='Reward Triggers'!H18*0.3*Inputs!$B$23*'VIP Levels'!$B$22*Revenue!H10 | I7: ='Reward Triggers'!I18*0.3*Inputs!$B$23*'VIP Levels'!$B$22*Revenue!I10 | ... M7: ='Reward Triggers'!M18*0.3*Inputs!$B$23*'VIP Levels'!$B$22*Revenue!M10
A8: Discount Cost (Margin Erosion) | B8: =Revenue!B12 | C8: =Revenue!C12 | D8: =Revenue!D12 | E8: =Revenue!E12 | F8: =Revenue!F12 | G8: =Revenue!G12 | H8: =Revenue!H12 | I8: =Revenue!I12 | ... M8: =Revenue!M12
A9: Total CM1 Costs | B9: =SUM(B5:B8) | C9: =SUM(C5:C8) | D9: =SUM(D5:D8) | E9: =SUM(E5:E8) | F9: =SUM(F5:F8) | G9: =SUM(G5:G8) | H9: =SUM(H5:H8) | I9: =SUM(I5:I8) | ... M9: =SUM(M5:M8)
A11: --- LOYALTY PROGRAM COSTS ---
A12: Gift Card Cost (Welcome) | B12: ='Reward Triggers'!B6*'VIP Levels'!$B$23 | C12: ='Reward Triggers'!C6*'VIP Levels'!$B$23 | D12: ='Reward Triggers'!D6*'VIP Levels'!$B$23 | E12: ='Reward Triggers'!E6*'VIP Levels'!$B$23 | F12: ='Reward Triggers'!F6*'VIP Levels'!$B$23 | G12: ='Reward Triggers'!G6*'VIP Levels'!$B$23 | H12: ='Reward Triggers'!H6*'VIP Levels'!$B$23 | I12: ='Reward Triggers'!I6*'VIP Levels'!$B$23 | ... M12: ='Reward Triggers'!M6*'VIP Levels'!$B$23
A13: Gift Card Cost (Missions) | B13: ='Reward Triggers'!B18*0.5*75 | C13: ='Reward Triggers'!C18*0.5*75 | D13: ='Reward Triggers'!D18*0.5*75 | E13: ='Reward Triggers'!E18*0.5*75 | F13: ='Reward Triggers'!F18*0.5*75 | G13: ='Reward Triggers'!G18*0.5*75 | H13: ='Reward Triggers'!H18*0.5*75 | I13: ='Reward Triggers'!I18*0.5*75 | ... M13: ='Reward Triggers'!M18*0.5*75
A14: Total Gift Card Cost | B14: =B12+B13 | C14: =C12+C13 | D14: =D12+D13 | E14: =E12+E13 | F14: =F12+F13 | G14: =G12+G13 | H14: =H12+H13 | I14: =I12+I13 | ... M14: =M12+M13
A15: Total Loyalty Program Costs | B15: =B14 | C15: =C14 | D15: =D14 | E15: =E14 | F15: =F14 | G15: =G14 | H15: =H14 | I15: =I14 | ... M15: =M14
A17: --- MARKETING OPEX ---
A18: Spark Ads Cost (Welcome) | B18: ='Reward Triggers'!B8*'VIP Levels'!$B$24 | C18: ='Reward Triggers'!C8*'VIP Levels'!$B$24 | D18: ='Reward Triggers'!D8*'VIP Levels'!$B$24 | E18: ='Reward Triggers'!E8*'VIP Levels'!$B$24 | F18: ='Reward Triggers'!F8*'VIP Levels'!$B$24 | G18: ='Reward Triggers'!G8*'VIP Levels'!$B$24 | H18: ='Reward Triggers'!H8*'VIP Levels'!$B$24 | I18: ='Reward Triggers'!I8*'VIP Levels'!$B$24 | ... M18: ='Reward Triggers'!M8*'VIP Levels'!$B$24
A19: Spark Ads Cost (Missions) | B19: ='Reward Triggers'!B18*0.2*50 | C19: ='Reward Triggers'!C18*0.2*50 | D19: ='Reward Triggers'!D18*0.2*50 | E19: ='Reward Triggers'!E18*0.2*50 | F19: ='Reward Triggers'!F18*0.2*50 | G19: ='Reward Triggers'!G18*0.2*50 | H19: ='Reward Triggers'!H18*0.2*50 | I19: ='Reward Triggers'!I18*0.2*50 | ... M19: ='Reward Triggers'!M18*0.2*50
A20: Physical Gift Cost | B20: ='Reward Triggers'!B9*'VIP Levels'!$B$25 | C20: ='Reward Triggers'!C9*'VIP Levels'!$B$25 | D20: ='Reward Triggers'!D9*'VIP Levels'!$B$25 | E20: ='Reward Triggers'!E9*'VIP Levels'!$B$25 | F20: ='Reward Triggers'!F9*'VIP Levels'!$B$25 | G20: ='Reward Triggers'!G9*'VIP Levels'!$B$25 | H20: ='Reward Triggers'!H9*'VIP Levels'!$B$25 | I20: ='Reward Triggers'!I9*'VIP Levels'!$B$25 | ... M20: ='Reward Triggers'!M9*'VIP Levels'!$B$25
A21: Experience Cost | B21: ='Reward Triggers'!B10*'VIP Levels'!$B$26 | C21: ='Reward Triggers'!C10*'VIP Levels'!$B$26 | D21: ='Reward Triggers'!D10*'VIP Levels'!$B$26 | E21: ='Reward Triggers'!E10*'VIP Levels'!$B$26 | F21: ='Reward Triggers'!F10*'VIP Levels'!$B$26 | G21: ='Reward Triggers'!G10*'VIP Levels'!$B$26 | H21: ='Reward Triggers'!H10*'VIP Levels'!$B$26 | I21: ='Reward Triggers'!I10*'VIP Levels'!$B$26 | ... M21: ='Reward Triggers'!M10*'VIP Levels'!$B$26
A22: Sample Cost | B22: ='Affiliate Projection'!B4*Inputs!$B$28 | C22: ='Affiliate Projection'!C4*Inputs!$B$28 | D22: ='Affiliate Projection'!D4*Inputs!$B$28 | E22: ='Affiliate Projection'!E4*Inputs!$B$28 | F22: ='Affiliate Projection'!F4*Inputs!$B$28 | G22: ='Affiliate Projection'!G4*Inputs!$B$28 | H22: ='Affiliate Projection'!H4*Inputs!$B$28 | I22: ='Affiliate Projection'!I4*Inputs!$B$28 | ... M22: ='Affiliate Projection'!M4*Inputs!$B$28
A23: Total Marketing OpEx | B23: =SUM(B18:B22) | C23: =SUM(C18:C22) | D23: =SUM(D18:D22) | E23: =SUM(E18:E22) | F23: =SUM(F18:F22) | G23: =SUM(G18:G22) | H23: =SUM(H18:H22) | I23: =SUM(I18:I22) | ... M23: =SUM(M18:M22)
A25: --- TOTALS ---
A26: Total Program Cost | B26: =B9+B15+B23 | C26: =C9+C15+C23 | D26: =D9+D15+D23 | E26: =E9+E15+E23 | F26: =F9+F15+F23 | G26: =G9+G15+G23 | H26: =H9+H15+H23 | I26: =I9+I15+I23 | ... M26: =M9+M15+M23

Sheet Summary
A1: SUMMARY DASHBOARD
A3: 12-MONTH TOTALS
A4: Metric | B4: Value
A5: Total Samples Sent | B5: =SUM('Affiliate Projection'!B4:M4)
A6: Total New Affiliates | B6: =SUM('Affiliate Projection'!B7:M7)
A7: Active Affiliates (Month 12) | B7: ='Affiliate Projection'!M9
A8: Total Sales | B8: =SUM('Affiliate Projection'!B10:M10)
A10: Gross Revenue | B10: =SUM(Revenue!B6:M6)
A11: Net Revenue | B11: =SUM(Revenue!B11:M11)
A13: Total CM1 Costs | B13: =SUM(Costs!B9:M9)
A14: Total Loyalty Program Costs | B14: =SUM(Costs!B15:M15)
A15: Total Marketing OpEx | B15: =SUM(Costs!B23:M23)
A16: Total Program Cost | B16: =SUM(Costs!B26:M26)
A19: KEY RATIOS
A20: Metric | B20: Value
A21: CM1 as % of Net Revenue | B21: =IF(B11>0,B13/B11,0)
A22: Total Cost as % of Net Revenue | B22: =IF(B11>0,B16/B11,0)
A23: Cost per Affiliate (12-mo avg) | B23: =IF(B6>0,B16/B6,0)
A24: Revenue per Affiliate (12-mo avg) | B24: =IF(B6>0,B11/B6,0)
A25: Sample-to-Affiliate Conversion | B25: =IF(B5>0,B6/B5,0)
A26: Weighted Avg Commission Rate | B26: =SUMPRODUCT('VIP Levels'!$D$5:$D$9,Inputs!$B$34:$B$38)
A29: MONTHLY TREND
A30: Metric | B30: M1 | C30: M2 | D30: M3 | E30: M4 | F30: M5 | G30: M6 | H30: M7 | I30: M8 | J30: M9 | K30: M10 | L30: M11 | M30: M12 | N30: Total
A31: Active Affiliates | B31: ='Affiliate Projection'!B9 | C31: ='Affiliate Projection'!C9 | D31: ='Affiliate Projection'!D9 | E31: ='Affiliate Projection'!E9 | F31: ='Affiliate Projection'!F9 | G31: ='Affiliate Projection'!G9 | H31: ='Affiliate Projection'!H9 | I31: ='Affiliate Projection'!I9 | ... M31: ='Affiliate Projection'!M9 | N31: =M31
A32: Total Sales | B32: ='Affiliate Projection'!B10 | C32: ='Affiliate Projection'!C10 | D32: ='Affiliate Projection'!D10 | E32: ='Affiliate Projection'!E10 | F32: ='Affiliate Projection'!F10 | G32: ='Affiliate Projection'!G10 | H32: ='Affiliate Projection'!H10 | I32: ='Affiliate Projection'!I10 | ... M32: ='Affiliate Projection'!M10 | N32: =SUM(B32:M32)
A33: Net Revenue | B33: =Revenue!B11 | C33: =Revenue!C11 | D33: =Revenue!D11 | E33: =Revenue!E11 | F33: =Revenue!F11 | G33: =Revenue!G11 | H33: =Revenue!H11 | I33: =Revenue!I11 | ... M33: =Revenue!M11 | N33: =SUM(B33:M33)
A34: Total Program Cost | B34: =Costs!B26 | C34: =Costs!C26 | D34: =Costs!D26 | E34: =Costs!E26 | F34: =Costs!F26 | G34: =Costs!G26 | H34: =Costs!H26 | I34: =Costs!I26 | ... M34: =Costs!M26 | N34: =SUM(B34:M34)
A35: Cost as % of Revenue | B35: =IF(B33>0,B34/B33,0) | C35: =IF(C33>0,C34/C33,0) | D35: =IF(D33>0,D34/D33,0) | E35: =IF(E33>0,E34/E33,0) | F35: =IF(F33>0,F34/F33,0) | G35: =IF(G33>0,G34/G33,0) | H35: =IF(H33>0,H34/H33,0) | I35: =IF(I33>0,I34/I33,0) | ... N35: =IF(N33>0,N34/N33,0)
